hyperparameter_hunter/VERSION
hyperparameter_hunter/__init__.py
hyperparameter_hunter/algorithm_handlers.py
hyperparameter_hunter/environment.py
hyperparameter_hunter/exceptions.py
hyperparameter_hunter/experiment_core.py
hyperparameter_hunter/experiments.py
hyperparameter_hunter/feature_engineering.py
hyperparameter_hunter/importer.py
hyperparameter_hunter/leaderboards.py
hyperparameter_hunter/metrics.py
hyperparameter_hunter/models.py
hyperparameter_hunter/recorders.py
hyperparameter_hunter/reporting.py
hyperparameter_hunter/result_reader.py
hyperparameter_hunter/sentinels.py
hyperparameter_hunter/settings.py
hyperparameter_hunter/tracers.py
hyperparameter_hunter/callbacks/__init__.py
hyperparameter_hunter/callbacks/aggregators.py
hyperparameter_hunter/callbacks/bases.py
hyperparameter_hunter/callbacks/evaluators.py
hyperparameter_hunter/callbacks/loggers.py
hyperparameter_hunter/callbacks/recipes.py
hyperparameter_hunter/callbacks/wranglers/__init__.py
hyperparameter_hunter/callbacks/wranglers/input_wranglers.py
hyperparameter_hunter/callbacks/wranglers/predictors.py
hyperparameter_hunter/callbacks/wranglers/target_wranglers.py
hyperparameter_hunter/data/__init__.py
hyperparameter_hunter/data/data_core.py
hyperparameter_hunter/data/datasets.py
hyperparameter_hunter/data/data_chunks/__init__.py
hyperparameter_hunter/data/data_chunks/input_chunks.py
hyperparameter_hunter/data/data_chunks/prediction_chunks.py
hyperparameter_hunter/data/data_chunks/target_chunks.py
hyperparameter_hunter/keys/__init__.py
hyperparameter_hunter/keys/hashing.py
hyperparameter_hunter/keys/makers.py
hyperparameter_hunter/library_helpers/__init__.py
hyperparameter_hunter/library_helpers/keras_helper.py
hyperparameter_hunter/library_helpers/keras_optimization_helper.py
hyperparameter_hunter/optimization/__init__.py
hyperparameter_hunter/optimization/protocol_core.py
hyperparameter_hunter/optimization/backends/__init__.py
hyperparameter_hunter/optimization/backends/skopt/LICENSE
hyperparameter_hunter-3.0.0.dist-info/AUTHORS.md
hyperparameter_hunter-3.0.0.dist-info/LICENSE
hyperparameter_hunter-3.0.0.dist-info/METADATA
hyperparameter_hunter-3.0.0.dist-info/WHEEL
hyperparameter_hunter-3.0.0.dist-info/top_level.txt
hyperparameter_hunter-3.0.0.dist-info/RECORD
