Metadata-Version: 2.1
Name: hyperparameter-hunter
Version: 3.0.0
Summary: Easy hyperparameter optimization and automatic result saving across machine learning algorithms and libraries
Home-page: https://github.com/HunterMcGushion/hyperparameter_hunter
Author: Hunter McGushion
Author-email: hunter@mcgushion.com
License: MIT
Keywords: hyperparameter tuning optimization machine learning artificial intelligence neural network keras scikit-learn xgboost catboost lightgbm rgf
Platform: UNKNOWN
Classifier: Intended Audience :: Developers
Classifier: Intended Audience :: Education
Classifier: Intended Audience :: Information Technology
Classifier: Intended Audience :: Science/Research
Classifier: License :: OSI Approved :: MIT License
Classifier: Operating System :: OS Independent
Classifier: Programming Language :: Python :: 3
Classifier: Topic :: Utilities
Classifier: Topic :: Desktop Environment :: File Managers
Classifier: Topic :: Education
Classifier: Topic :: Scientific/Engineering
Classifier: Topic :: Scientific/Engineering :: Artificial Intelligence
Classifier: Topic :: Scientific/Engineering :: Human Machine Interfaces
Classifier: Topic :: Scientific/Engineering :: Information Analysis
Classifier: Topic :: Scientific/Engineering :: Mathematics
Classifier: Topic :: Software Development
Classifier: Topic :: Software Development :: Libraries :: Python Modules
Requires-Dist: dill
Requires-Dist: nbconvert
Requires-Dist: nbformat
Requires-Dist: numpy
Requires-Dist: pandas
Requires-Dist: scikit-learn
Requires-Dist: scikit-optimize
Requires-Dist: scipy
Requires-Dist: simplejson
Requires-Dist: wrapt
Provides-Extra: dev
Requires-Dist: pre-commit ; extra == 'dev'
Provides-Extra: docs
Requires-Dist: numpydoc ; extra == 'docs'
Requires-Dist: hyperparameter-hunter ; extra == 'docs'
Requires-Dist: keras ; extra == 'docs'
Provides-Extra: travis
Requires-Dist: pytest (>=4.0) ; extra == 'travis'
Requires-Dist: pytest-cov ; extra == 'travis'
Requires-Dist: black ; extra == 'travis'
Requires-Dist: hyperparameter-hunter ; extra == 'travis'
Requires-Dist: keras ; extra == 'travis'
Requires-Dist: tensorflow ; extra == 'travis'
Requires-Dist: xgboost ; extra == 'travis'
Requires-Dist: coveralls ; extra == 'travis'
Requires-Dist: codecov ; extra == 'travis'
